{
    "authors": {
        "BIGxixi": {
            "pixiv": "https://www.pixiv.net/en/users/26690900",
            "twitter": "https://twitter.com/bigxixiii"
        }
    },
    "files": [
        {
            "source": "https://drive.google.com/uc?export=view&id=1BFfCQtVaiys7hGknTEMt6nkvijbWpmnu",
            "name": "白丝袜",
            "mimeType": "image",
            "tags": ["c3RvY2tpbmdz"],
            "author": "BIGxixi"
        },
        {
            "source": "https://drive.google.com/uc?export=view&id=1LI6CxfMSis0f1F_wklwg0gCg3vgHPqZl",
            "name": "Kiara 秋",
            "mimeType": "image",
            "author": "BIGxixi"
        },
        {
            "source": "https://drive.google.com/uc?export=view&id=19w64qb7YrNAZ8FwIx2n89I4_yPhr2eVB",
            "name": "Kiara 夏",
            "mimeType": "image",
            "author": "BIGxixi"
        },
        {
            "source": "https://drive.google.com/uc?export=view&id=1Te72sBylpnz51cu77B-DOHaURvPO5XVG",
            "name": "KIARA 春 16:9",
            "mimeType": "image",
            "author": "BIGxixi"
        },
        {
            "source": "https://drive.google.com/uc?export=view&id=12_b29_DGDUv22e-WzuR43bEKh9fttNJK",
            "name": "Saber",
            "mimeType": "image",
            "author": "BIGxixi"
        },
        {
            "source": "https://drive.google.com/uc?export=view&id=1BzUQsexFkuSbObbps8ztQVvQBpG5-gr4",
            "name": "❄❄",
            "mimeType": "image",
            "author": "BIGxixi"
        }
    ]
}
